odds_helpers/__init__.py
odds_helpers/odds_helpers.py
odds_helpers-0.0.2.dist-info/METADATA
odds_helpers-0.0.2.dist-info/WHEEL
odds_helpers-0.0.2.dist-info/licenses/LICENSE
odds_helpers-0.0.2.dist-info/RECORD
