Metadata-Version: 2.4
Name: odds-helpers
Version: 0.0.2
Summary: A series of useful functions in betting.
Author-email: Deep Pulusani <deep.pulusani@gmail.com>
License-Expression: MIT
License-File: LICENSE
Classifier: Operating System :: OS Independent
Classifier: Programming Language :: Python :: 3
Requires-Python: >=3.1
